brothon/__init__.py
brothon/bro_log_reader.py
brothon/bro_multi_log_reader.py
brothon/live_simulator.py
brothon/analysis/__init__.py
brothon/analysis/data_generator.py
brothon/analysis/dataframe_cache.py
brothon/analysis/dataframe_stats.py
brothon/analysis/dataframe_to_matrix.py
brothon/analysis/dummy_encoder.py
brothon/analysis/ngrams.py
brothon/utils/__init__.py
brothon/utils/cache.py
brothon/utils/dir_watcher.py
brothon/utils/file_tailer.py
brothon/utils/file_utils.py
brothon/utils/plot_utils.py
brothon/utils/signal_utils.py
brothon/utils/vt_query.py
brothon-0.2.5.data/data/data/app_stats.log
brothon-0.2.5.data/data/data/conn.log
brothon-0.2.5.data/data/data/dhcp.log
brothon-0.2.5.data/data/data/dhcp.log.gz
brothon-0.2.5.data/data/data/dhcp_002.log
brothon-0.2.5.data/data/data/dhcp_002.log.gz
brothon-0.2.5.data/data/data/dns.log
brothon-0.2.5.data/data/data/files.log
brothon-0.2.5.data/data/data/ftp.log
brothon-0.2.5.data/data/data/http.log
brothon-0.2.5.data/data/data/http.log.gz
brothon-0.2.5.data/data/data/notice.log
brothon-0.2.5.data/data/data/phishing_sites.txt
brothon-0.2.5.data/data/data/smtp.log
brothon-0.2.5.data/data/data/ssl.log
brothon-0.2.5.data/data/data/weird.log
brothon-0.2.5.data/data/data/x509.log
brothon-0.2.5.data/data/examples/anomaly_detection.py
brothon-0.2.5.data/data/examples/anomaly_detection_streaming.py
brothon-0.2.5.data/data/examples/anomaly_detection_streaming_hdbscan.py
brothon-0.2.5.data/data/examples/bro_kafka.py
brothon-0.2.5.data/data/examples/bro_pprint.py
brothon-0.2.5.data/data/examples/bro_to_pandas.py
brothon-0.2.5.data/data/examples/bro_to_scikit.py
brothon-0.2.5.data/data/examples/cert_checker.py
brothon-0.2.5.data/data/examples/dns_demo.log
brothon-0.2.5.data/data/examples/file_log_vtquery.py
brothon-0.2.5.data/data/examples/girder_anomaly.py
brothon-0.2.5.data/data/examples/http_user_agents.py
brothon-0.2.5.data/data/examples/kafka_producer.py
brothon-0.2.5.dist-info/DESCRIPTION.rst
brothon-0.2.5.dist-info/METADATA
brothon-0.2.5.dist-info/RECORD
brothon-0.2.5.dist-info/WHEEL
brothon-0.2.5.dist-info/metadata.json
brothon-0.2.5.dist-info/top_level.txt
