Metadata-Version: 2.0
Name: brothon
Version: 0.2.5
Summary: Bro + Python = Brothon!
Home-page: https://github.com/kitware/BroThon
Author: Brian Wylie
Author-email: brian.wylie@kitware.com
License: Apache
Keywords: Bro IDS,Python,Networking,Security
Platform: UNKNOWN
Classifier: Development Status :: 2 - Pre-Alpha
Classifier: Intended Audience :: Developers
Classifier: License :: OSI Approved :: Apache Software License
Classifier: Natural Language :: English
Classifier: Programming Language :: Python :: 2.7
Classifier: Programming Language :: Python :: 3.5
Classifier: Programming Language :: Python :: 3.6
Classifier: Programming Language :: Python :: Implementation :: CPython
Classifier: Programming Language :: Python :: Implementation :: PyPy
Requires-Dist: pandas
Requires-Dist: requests
Requires-Dist: scikit-learn
Requires-Dist: scipy
Requires-Dist: watchdog
Provides-Extra: all
Requires-Dist: tldextract; extra == 'all'
Requires-Dist: yara-python; extra == 'all'
